lybraries/__init__.py
lybraries-1.0.0.dist-info/LICENSE
lybraries-1.0.0.dist-info/METADATA
lybraries-1.0.0.dist-info/WHEEL
lybraries-1.0.0.dist-info/top_level.txt
lybraries-1.0.0.dist-info/RECORD
