Metadata-Version: 2.1
Name: lybraries
Version: 1.0.0
Summary: API wrapper for libraries.io
Home-page: https://github.com/weerdy15/lybraries
Author: weerdy15
License: MIT
Project-URL: Issue tracker, https://github.com/weerdy15/lybraries/issues
Platform: UNKNOWN
Classifier: Development Status :: 1 - Planning
Classifier: Intended Audience :: Developers
Classifier: Natural Language :: English
Classifier: Programming Language :: Python :: 3.8
Classifier: Programming Language :: Python :: 3.9
Classifier: Programming Language :: Python :: 3.10
Classifier: Topic :: Utilities
Requires-Python: >=3.8.0
License-File: LICENSE
